pywxtool/__init__.py
pywxtool/wxtool.py
pywxtool/libs/libcrypto-1_1-x64.dll
pywxtool/libs/libssl-1_1-x64.dll
pywxtool/libs/wxtool.dll
pywxtool-1.0.4.dist-info/METADATA
pywxtool-1.0.4.dist-info/WHEEL
pywxtool-1.0.4.dist-info/top_level.txt
pywxtool-1.0.4.dist-info/RECORD
