Metadata-Version: 2.1
Name: pywxtool
Version: 1.0.4
Summary: 微信信息获取工具
Home-page: https://github.com/xaoyaoo
Author: xaoyaoo
Author-email: xaoyaoo@gmail.com
License: MIT
Classifier: Programming Language :: Python :: 3
Classifier: Operating System :: OS Independent
Requires-Python: >=3.8, <4
Requires-Dist: setuptools >=42
Requires-Dist: wheel
